visualimiss/__init__.py
visualimiss/utils.py
visualimiss/visualimiss.py
visualimiss-0.0.7.dist-info/LICENSE
visualimiss-0.0.7.dist-info/METADATA
visualimiss-0.0.7.dist-info/WHEEL
visualimiss-0.0.7.dist-info/top_level.txt
visualimiss-0.0.7.dist-info/RECORD
