Metadata-Version: 2.1
Name: visualimiss
Version: 0.0.7
Summary: Visualize missing data
Author: ngntrgduc
Project-URL: Homepage, https://github.com/ngntrgduc/visualimiss
Project-URL: Bug Tracker, https://github.com/ngntrgduc/visualimiss/issues
Keywords: data,data visualization,missing data
Requires-Python: >=3.7
License-File: LICENSE
Requires-Dist: numpy
Requires-Dist: pandas
Requires-Dist: matplotlib
